{
  "@context": "http://iiif.io/api/presentation/2/context.json",
  "@id": "http://rspace.library.cofc.edu/iiif/lcdl125408JPEG1jpg/manifest",
  "@type": "sc:Manifest",
  "label": "Corn Exhibit",
  "description": "A black and white photograph of the Charleston Chamber of Commerce corn exhibit at the arcade mall in Columbia, South Carolina.  The exhibit took place during the National Corn Show which was being held in Dallas, TX on February 10-24, 1914.  A pennant reading, 'Charleston, SC' can be seen hanging in one of the windows among other patriotic decorations.  Two men, W. McLeod Frampton and L.H. Mixson are in the photograph by the exhibit.",
  "metadata": [
    {
      "label": "Streaming URL",
      "value": ""
    },
    {
      "label": "Description",
      "value": "A black and white photograph of the Charleston Chamber of Commerce corn exhibit at the arcade mall in Columbia, South Carolina.  The exhibit took place during the National Corn Show which was being held in Dallas, TX on February 10-24, 1914.  A pennant reading, 'Charleston, SC' can be seen hanging in one of the windows among other patriotic decorations.  Two men, W. McLeod Frampton and L.H. Mixson are in the photograph by the exhibit."
    },
    {
      "label": "Access Note",
      "value": ""
    },
    {
      "label": "Access Statement",
      "value": ""
    },
    {
      "label": "Contributing Institution",
      "value": [
        {
          "@value": "South Carolina Historical Society",
          "@language": "en"
        }
      ]
    },
    {
      "label": "Copyright Status Statement",
      "value": "Copyright status undetermined."
    },
    {
      "label": "Date Digital",
      "value": ""
    },
    {
      "label": "Digitization Specifications",
      "value": "600 dpi, 16-bit depth, black and white, Epson Expression 12000XL, Archival masters are tiffs."
    },
    {
      "label": "Transcript",
      "value": ""
    },
    {
      "label": "Format",
      "value": ""
    },
    {
      "label": "Media Type",
      "value": [
        {
          "@value": "Images",
          "@language": "en"
        }
      ]
    },
    {
      "label": "S.C. County",
      "value": [

      ]
    },
    {
      "label": "Resource Locator",
      "value": "251"
    },
    {
      "label": "Type",
      "value": [
        {
          "@value": "StillImage",
          "@language": "en"
        }
      ]
    },
    {
      "label": "PID",
      "value": "lcdl:125408"
    },
    {
      "label": "Collection Identifier",
      "value": "schsvis"
    },
    {
      "label": "Original filename",
      "value": "lcdl125408-JPEG1.jpg"
    },
    {
      "label": "Collection Title",
      "value": "Agricultural Society of South Carolina Visual Materials"
    },
    {
      "label": "Location",
      "value": ""
    },
    {
      "label": "Interviewer",
      "value": ""
    },
    {
      "label": "Interviewee",
      "value": ""
    },
    {
      "label": "Speaker",
      "value": ""
    },
    {
      "label": "Contributor",
      "value": ""
    },
    {
      "label": "Alternate Title",
      "value": ""
    },
    {
      "label": "Subtitle",
      "value": ""
    },
    {
      "label": "Abstract",
      "value": ""
    },
    {
      "label": "Note",
      "value": ""
    },
    {
      "label": "Biographical Note",
      "value": ""
    },
    {
      "label": "Creator Note",
      "value": ""
    },
    {
      "label": "Collection Note",
      "value": ""
    },
    {
      "label": "Location Record",
      "value": ""
    },
    {
      "label": "Condition Evaluation Note",
      "value": ""
    },
    {
      "label": "Extent",
      "value": ""
    },
    {
      "label": "Duration",
      "value": ""
    },
    {
      "label": "Series Title",
      "value": [

      ]
    },
    {
      "label": "Subseries Title",
      "value": [
        {
          "@value": "StillImage,Columbia (S.C.),Richland County (S.C.),Agriculture--South Carolina,1914,English,South Carolina Historical Society,Lexington County (S.C.),Charleston Chamber of Commerce,Images,Dallas (Tex.),Frampton, W. McLeod (William McLeod), 1892-1979,Corn,Agricultural exhibitions,Arcades,Architecture, Italian--United States",
          "@language": "en"
        }
      ]
    },
    {
      "label": "Locator",
      "value": ""
    },
    {
      "label": "Photo ID",
      "value": ""
    },
    {
      "label": "Portfolio Title",
      "value": ""
    },
    {
      "label": "Portfolio Number",
      "value": ""
    },
    {
      "label": "Folder Number",
      "value": ""
    },
    {
      "label": "Region",
      "value": ""
    },
    {
      "label": "Physical Description",
      "value": ""
    },
    {
      "label": "Original Format",
      "value": ""
    },
    {
      "label": "Type AAT",
      "value": ""
    },
    {
      "label": "Type DCMI",
      "value": ""
    },
    {
      "label": "Type IMT",
      "value": "image/jpeg"
    },
    {
      "label": "Citation",
      "value": ""
    },
    {
      "label": "Resource Type",
      "value": ""
    },
    {
      "label": "iiif",
      "value": "lcdl125408JPEG1jpg"
    },
    {
      "label": "Compound Identifier",
      "value": "schsvis"
    },
    {
      "label": "Subject - Temporal",
      "value": [
        {
          "@value": "StillImage,Columbia (S.C.),Richland County (S.C.),Agriculture--South Carolina,1914,English,South Carolina Historical Society,Lexington County (S.C.),Charleston Chamber of Commerce,Images,Dallas (Tex.),Frampton, W. McLeod (William McLeod), 1892-1979,Corn,Agricultural exhibitions,Arcades,Architecture, Italian--United States",
          "@language": "en"
        }
      ]
    },
    {
      "label": "Shelving Locator",
      "value": "251"
    },
    {
      "label": "Subject - Geographic Region",
      "value": ""
    },
    {
      "label": "Subject - Geographic County",
      "value": [
        {
          "@value": "Richland County (S.C.),Lexington County (S.C.)",
          "@language": "en"
        }
      ]
    },
    {
      "label": "Title",
      "value": "Corn Exhibit"
    },
    {
      "label": "Subject - Geographic",
      "value": [
        {
          "@value": "Columbia (S.C.),Dallas (Tex.)",
          "@language": "en"
        }
      ]
    },
    {
      "label": "Subject - Topical",
      "value": [
        {
          "@value": "Agriculture--South Carolina,Corn,Agricultural exhibitions,Arcades,Architecture, Italian--United States",
          "@language": "en"
        }
      ]
    },
    {
      "label": "Subject - Name",
      "value": [
        {
          "@value": "Charleston Chamber of Commerce,Frampton, W. McLeod (William McLeod), 1892-1979",
          "@language": "en"
        }
      ]
    },
    {
      "label": "Creator Name (Corporate)",
      "value": [

      ]
    },
    {
      "label": "Creator Name (Personal)",
      "value": [

      ]
    },
    {
      "label": "Date",
      "value": [
        {
          "@value": "1914",
          "@language": "en"
        }
      ]
    },
    {
      "label": "Language",
      "value": [
        {
          "@value": "English",
          "@language": "en"
        }
      ]
    },
    {
      "label": "Notes",
      "value": ""
    }
  ],
  "license": "Copyright status undetermined.",
  "thumbnail": {
    "@id": "http://153.9.109.68:8080/cantaloupe-4.0.1/iiif/2/42831/full/thm/0/default.jpg",
    "@type": "dctypes:Image",
    "height": 122,
    "width": 150,
    "format": "image/jpeg",
    "service": {
      "@context": "http://iiif.io/api/image/2/context.json",
      "@id": "http://153.9.109.68:8080/cantaloupe-4.0.1/iiif/2/42831",
      "profile": "http://iiif.io/api/image/2/level1.json"
    }
  },
  "sequences": [
    {
      "@id": "http://rspace.library.cofc.edu/iiif/lcdl125408JPEG1jpg/sequence/normal",
      "@type": "sc:Sequence",
      "label": "Default order",
      "canvases": [
        {
          "@id": "http://rspace.library.cofc.edu/iiif/lcdl125408JPEG1jpg/canvas/0",
          "@type": "sc:Canvas",
          "label": "0",
          "height": 1623,
          "width": 2000,
          "thumbnail": {
            "@id": "http://153.9.109.68:8080/cantaloupe-4.0.1/iiif/2/42831/full/thm/0/default.jpg",
            "@type": "dctypes:Image",
            "height": 122,
            "width": 150,
            "format": "image/jpeg",
            "service": {
              "@context": "http://iiif.io/api/image/2/context.json",
              "@id": "http://153.9.109.68:8080/cantaloupe-4.0.1/iiif/2/42831",
              "profile": "http://iiif.io/api/image/2/level1.json"
            }
          },
          "images": [
            {
              "@context": "http://iiif.io/api/presentation/2/context.json",
              "@id": "http://rspace.library.cofc.edu/iiif/lcdl125408JPEG1jpg/annotation/0",
              "@type": "oa:Annotation",
              "motivation": "sc:painting",
              "resource": {
                "@id": "http://153.9.109.68:8080/cantaloupe-4.0.1/iiif/2/42831/full/full/0/default.jpg",
                "@type": "dctypes:Image",
                "format": "image/jpeg",
                "service": {
                  "@context": "http://iiif.io/api/image/2/context.json",
                  "@id": "http://153.9.109.68:8080/cantaloupe-4.0.1/iiif/2/42831",
                  "profile": "http://iiif.io/api/image/2/level1.json"
                }
              },
              "on": "http://rspace.library.cofc.edu/iiif/lcdl125408JPEG1jpg/canvas/0",
              "height": 1623,
              "width": 2000
            }
          ]
        }
      ]
    }
  ]
}