{
  "@context": "http://iiif.io/api/presentation/2/context.json",
  "@id": "https://rspace.library.cofc.edu/iiif/lcdl1968JPEG1jpg/manifest",
  "@type": "sc:Manifest",
  "label": "Man writing at table.",
  "description": "7.6 x 7.7 cm photographic print",
  "metadata": [
    {
      "label": "Description",
      "value": "7.6 x 7.7 cm photographic print"
    },
    {
      "label": "Contributing Institution",
      "value": [
        {
          "@value": "Beaufort County Library",
          "@language": "en"
        }
      ]
    },
    {
      "label": "Copyright Status Statement",
      "value": "Digital image copyright 2008, Beaufort County Library. All rights reserved. For more information contact the Beaufort County Library, Beaufort, SC 29902."
    },
    {
      "label": "Date Digital",
      "value": "2008-04"
    },
    {
      "label": "Digitization Specifications",
      "value": "1600 ppi, 24-bit depth, color, Epson Expression 10000XL, Archival Masters are tiffs."
    },
    {
      "label": "Media Type",
      "value": [
        {
          "@value": "Images",
          "@language": "en"
        }
      ]
    },
    {
      "label": "Resource Locator",
      "value": "1:30e"
    },
    {
      "label": "Type",
      "value": [
        {
          "@value": "StillImage",
          "@language": "en"
        }
      ]
    },
    {
      "label": "PID",
      "value": "lcdl:1968"
    },
    {
      "label": "Collection Identifier",
      "value": "PFF"
    },
    {
      "label": "Original filename",
      "value": "lcdl1968-JPEG1.jpg"
    },
    {
      "label": "Collection Title",
      "value": "Phosphate, Farms, & Family: The Donner Collection"
    },
    {
      "label": "Type IMT",
      "value": "image/jpeg"
    },
    {
      "label": "iiif",
      "value": "lcdl1968JPEG1jpg"
    },
    {
      "label": "Compound Identifier",
      "value": "PFF"
    },
    {
      "label": "Subject - Temporal",
      "value": [
        {
          "@value": "StillImage,English,Beaufort County Library,Images,unknown,Donner, Conrad Munro, 1844-1916,1889-1895,Interior decoration -- 1880-1920",
          "@language": "en"
        }
      ]
    },
    {
      "label": "Shelving Locator",
      "value": "1:30e"
    },
    {
      "label": "Subject - Geographic County",
      "value": [
        {
          "@value": "unknown",
          "@language": "en"
        }
      ]
    },
    {
      "label": "Title",
      "value": "Man writing at table."
    },
    {
      "label": "Subject - Topical",
      "value": [
        {
          "@value": "Interior decoration -- 1880-1920",
          "@language": "en"
        }
      ]
    },
    {
      "label": "Creator Name (Personal)",
      "value": [
        {
          "@value": "Donner, Conrad Munro, 1844-1916",
          "@language": "en"
        }
      ]
    },
    {
      "label": "Date",
      "value": [
        {
          "@value": "1889-1895",
          "@language": "en"
        }
      ]
    },
    {
      "label": "Language",
      "value": [
        {
          "@value": "English",
          "@language": "en"
        }
      ]
    }
  ],
  "license": "Digital image copyright 2008, Beaufort County Library. All rights reserved. For more information contact the Beaufort County Library, Beaufort, SC 29902.",
  "thumbnail": {
    "@id": "https://iiif.library.cofc.edu/iiif/2/58531/full/thm/0/default.jpg",
    "@type": "dctypes:Image",
    "height": 150,
    "width": 149,
    "format": "image/jpeg",
    "service": {
      "@context": "http://iiif.io/api/image/2/context.json",
      "@id": "https://iiif.library.cofc.edu/iiif/2/58531",
      "profile": "http://iiif.io/api/image/2/level1.json"
    }
  },
  "sequences": [
    {
      "@id": "https://rspace.library.cofc.edu/iiif/lcdl1968JPEG1jpg/sequence/normal",
      "@type": "sc:Sequence",
      "label": "Default order",
      "canvases": [
        {
          "@id": "https://rspace.library.cofc.edu/iiif/lcdl1968JPEG1jpg/canvas/0",
          "@type": "sc:Canvas",
          "label": "0",
          "height": 4762,
          "width": 4744,
          "thumbnail": {
            "@id": "https://iiif.library.cofc.edu/iiif/2/58531/full/thm/0/default.jpg",
            "@type": "dctypes:Image",
            "height": 150,
            "width": 149,
            "format": "image/jpeg",
            "service": {
              "@context": "http://iiif.io/api/image/2/context.json",
              "@id": "https://iiif.library.cofc.edu/iiif/2/58531",
              "profile": "http://iiif.io/api/image/2/level1.json"
            }
          },
          "images": [
            {
              "@context": "http://iiif.io/api/presentation/2/context.json",
              "@id": "https://rspace.library.cofc.edu/iiif/lcdl1968JPEG1jpg/annotation/0",
              "@type": "oa:Annotation",
              "motivation": "sc:painting",
              "resource": {
                "@id": "https://iiif.library.cofc.edu/iiif/2/58531/full/full/0/default.jpg",
                "@type": "dctypes:Image",
                "format": "image/jpeg",
                "service": {
                  "@context": "http://iiif.io/api/image/2/context.json",
                  "@id": "https://iiif.library.cofc.edu/iiif/2/58531",
                  "profile": "http://iiif.io/api/image/2/level1.json"
                }
              },
              "on": "https://rspace.library.cofc.edu/iiif/lcdl1968JPEG1jpg/canvas/0",
              "height": 4762,
              "width": 4744
            }
          ],
          "otherContent": [
            {
              "@context": "//iiif.io/api/presentation/2/context.json",
              "@id": "https://lcdl.library.cofc.edu/lcdl/collections/annotation?iiif_identifier=lcdl1968JPEG1jpg",
              "@type": "sc:AnnotationList"
            }
          ]
        }
      ]
    }
  ]
}