{
  "@context": "http://iiif.io/api/presentation/2/context.json",
  "@id": "https://rspace.library.cofc.edu/iiif/107130241fedoraExportdatalcdl118964lcdl118964JPEG1/manifest",
  "@type": "sc:Manifest",
  "label": "The General Practice Section Update, Vol. 1 No. 1, South Carolina Bar, November 1983",
  "description": "The General Practice Section Update is \"a publication of the general practice section of the South Carolina Bar,\" which was \"mailed to all South Carolina Bar Members.\" This particular document was mailed to Russell Brown, a Charleston Attorney.",
  "metadata": [
    {
      "label": "Description",
      "value": "The General Practice Section Update is \"a publication of the general practice section of the South Carolina Bar,\" which was \"mailed to all South Carolina Bar Members.\" This particular document was mailed to Russell Brown, a Charleston Attorney."
    },
    {
      "label": "Access Note",
      "value": "For more information contact archivist at the Avery Research Center, 125 Bull Street, Charleston, SC 29424."
    },
    {
      "label": "Access Statement",
      "value": "All rights reserved."
    },
    {
      "label": "Contributing Institution",
      "value": [
        {
          "@value": "Avery Research Center at the College of Charleston",
          "@language": "en"
        }
      ]
    },
    {
      "label": "Copyright Status Statement",
      "value": "Copyright © South Carolina Bar."
    },
    {
      "label": "Date Digital",
      "value": "2016-11"
    },
    {
      "label": "Digitization Specifications",
      "value": "300 dpi, 24-bit depth, color, Fujitsu fi-7160, Archival masters are tiffs."
    },
    {
      "label": "Media Type",
      "value": [
        {
          "@value": "Documents",
          "@language": "en"
        }
      ]
    },
    {
      "label": "Resource Locator",
      "value": "AMN 1117 Box 09 Folder 74"
    },
    {
      "label": "Type",
      "value": [
        {
          "@value": "Text",
          "@language": "en"
        }
      ]
    },
    {
      "label": "PID",
      "value": "lcdl:118964"
    },
    {
      "label": "Collection Identifier",
      "value": "AMN1117-127"
    },
    {
      "label": "Original filename",
      "value": "lcdl118964-JPEG1.jpg"
    },
    {
      "label": "Collection Title",
      "value": "Charleston Branch of the National Association for the Advancement of Colored People Papers, 1920-1995"
    },
    {
      "label": "Type IMT",
      "value": "image/jpeg"
    },
    {
      "label": "iiif",
      "value": "107130241fedoraExportdatalcdl118964lcdl118964JPEG1"
    },
    {
      "label": "Compound Identifier",
      "value": "AMN1117-127"
    },
    {
      "label": "Subject - Temporal",
      "value": [
        {
          "@value": "Text,Charleston (S.C.),African Americans--Civil rights,African Americans--Political activity,Charleston (S.C.)--Race relations,National Association for the Advancement of Colored People,National Association for the Advancement of Colored People. Charleston Branch (Charleston, S.C.),Avery Research Center at the College of Charleston,English,African Americans--South Carolina,1983-11,South Carolina Bar,Documents",
          "@language": "en"
        }
      ]
    },
    {
      "label": "Shelving Locator",
      "value": "AMN 1117 Box 09 Folder 74"
    },
    {
      "label": "Title",
      "value": "The General Practice Section Update, Vol. 1 No. 1, South Carolina Bar, November 1983"
    },
    {
      "label": "Subject - Geographic",
      "value": [
        {
          "@value": "Charleston (S.C.)",
          "@language": "en"
        }
      ]
    },
    {
      "label": "Subject - Topical",
      "value": [
        {
          "@value": "African Americans--Civil rights,African Americans--Political activity,Charleston (S.C.)--Race relations,National Association for the Advancement of Colored People,National Association for the Advancement of Colored People. Charleston Branch (Charleston, S.C.),African Americans--South Carolina",
          "@language": "en"
        }
      ]
    },
    {
      "label": "Creator Name (Corporate)",
      "value": [
        {
          "@value": "South Carolina Bar",
          "@language": "en"
        }
      ]
    },
    {
      "label": "Date",
      "value": [
        {
          "@value": "1983-11",
          "@language": "en"
        }
      ]
    },
    {
      "label": "Language",
      "value": [
        {
          "@value": "English",
          "@language": "en"
        }
      ]
    }
  ],
  "license": "Copyright © South Carolina Bar.",
  "thumbnail": {
    "@id": "https://iiif.library.cofc.edu/iiif/2/23516/full/thm/0/default.jpg",
    "@type": "dctypes:Image",
    "height": 150,
    "width": 114,
    "format": "image/jpeg",
    "service": {
      "@context": "http://iiif.io/api/image/2/context.json",
      "@id": "https://iiif.library.cofc.edu/iiif/2/23516",
      "profile": "http://iiif.io/api/image/2/level1.json"
    }
  },
  "sequences": [
    {
      "@id": "https://rspace.library.cofc.edu/iiif/AMN1117-127/sequence/normal",
      "@type": "sc:Sequence",
      "label": "Default order",
      "canvases": [
        {
          "@id": "https://rspace.library.cofc.edu/iiif/lcdl118965JPEG1jpg/canvas/0",
          "@type": "sc:Canvas",
          "label": "0",
          "height": 2000,
          "width": 1516,
          "thumbnail": {
            "@id": "https://iiif.library.cofc.edu/iiif/2/160879/full/thm/0/default.jpg",
            "@type": "dctypes:Image",
            "height": 150,
            "width": 114,
            "format": "image/jpeg",
            "service": {
              "@context": "http://iiif.io/api/image/2/context.json",
              "@id": "https://iiif.library.cofc.edu/iiif/2/160879",
              "profile": "http://iiif.io/api/image/2/level1.json"
            }
          },
          "images": [
            {
              "@context": "http://iiif.io/api/presentation/2/context.json",
              "@id": "https://rspace.library.cofc.edu/iiif/lcdl118965JPEG1jpg/annotation/0",
              "@type": "oa:Annotation",
              "motivation": "sc:painting",
              "resource": {
                "@id": "https://iiif.library.cofc.edu/iiif/2/160879/full/full/0/default.jpg",
                "@type": "dctypes:Image",
                "format": "image/jpeg",
                "service": {
                  "@context": "http://iiif.io/api/image/2/context.json",
                  "@id": "https://iiif.library.cofc.edu/iiif/2/160879",
                  "profile": "http://iiif.io/api/image/2/level1.json"
                }
              },
              "on": "https://rspace.library.cofc.edu/iiif/lcdl118965JPEG1jpg/canvas/0",
              "height": 2000,
              "width": 1516
            }
          ],
          "otherContent": [
            {
              "@context": "//iiif.io/api/presentation/2/context.json",
              "@id": "https://beta.lcdl.library.cofc.edu/lcdl/collections/annotation?iiif_identifier=lcdl118965JPEG1jpg",
              "@type": "sc:AnnotationList"
            }
          ]
        },
        {
          "@id": "https://rspace.library.cofc.edu/iiif/lcdl118966JPEG1jpg/canvas/0",
          "@type": "sc:Canvas",
          "label": "0",
          "height": 2000,
          "width": 1516,
          "thumbnail": {
            "@id": "https://iiif.library.cofc.edu/iiif/2/160880/full/thm/0/default.jpg",
            "@type": "dctypes:Image",
            "height": 150,
            "width": 114,
            "format": "image/jpeg",
            "service": {
              "@context": "http://iiif.io/api/image/2/context.json",
              "@id": "https://iiif.library.cofc.edu/iiif/2/160880",
              "profile": "http://iiif.io/api/image/2/level1.json"
            }
          },
          "images": [
            {
              "@context": "http://iiif.io/api/presentation/2/context.json",
              "@id": "https://rspace.library.cofc.edu/iiif/lcdl118966JPEG1jpg/annotation/0",
              "@type": "oa:Annotation",
              "motivation": "sc:painting",
              "resource": {
                "@id": "https://iiif.library.cofc.edu/iiif/2/160880/full/full/0/default.jpg",
                "@type": "dctypes:Image",
                "format": "image/jpeg",
                "service": {
                  "@context": "http://iiif.io/api/image/2/context.json",
                  "@id": "https://iiif.library.cofc.edu/iiif/2/160880",
                  "profile": "http://iiif.io/api/image/2/level1.json"
                }
              },
              "on": "https://rspace.library.cofc.edu/iiif/lcdl118966JPEG1jpg/canvas/0",
              "height": 2000,
              "width": 1516
            }
          ],
          "otherContent": [
            {
              "@context": "//iiif.io/api/presentation/2/context.json",
              "@id": "https://beta.lcdl.library.cofc.edu/lcdl/collections/annotation?iiif_identifier=lcdl118966JPEG1jpg",
              "@type": "sc:AnnotationList"
            }
          ]
        },
        {
          "@id": "https://rspace.library.cofc.edu/iiif/lcdl118967JPEG1jpg/canvas/0",
          "@type": "sc:Canvas",
          "label": "0",
          "height": 2000,
          "width": 1516,
          "thumbnail": {
            "@id": "https://iiif.library.cofc.edu/iiif/2/160881/full/thm/0/default.jpg",
            "@type": "dctypes:Image",
            "height": 150,
            "width": 114,
            "format": "image/jpeg",
            "service": {
              "@context": "http://iiif.io/api/image/2/context.json",
              "@id": "https://iiif.library.cofc.edu/iiif/2/160881",
              "profile": "http://iiif.io/api/image/2/level1.json"
            }
          },
          "images": [
            {
              "@context": "http://iiif.io/api/presentation/2/context.json",
              "@id": "https://rspace.library.cofc.edu/iiif/lcdl118967JPEG1jpg/annotation/0",
              "@type": "oa:Annotation",
              "motivation": "sc:painting",
              "resource": {
                "@id": "https://iiif.library.cofc.edu/iiif/2/160881/full/full/0/default.jpg",
                "@type": "dctypes:Image",
                "format": "image/jpeg",
                "service": {
                  "@context": "http://iiif.io/api/image/2/context.json",
                  "@id": "https://iiif.library.cofc.edu/iiif/2/160881",
                  "profile": "http://iiif.io/api/image/2/level1.json"
                }
              },
              "on": "https://rspace.library.cofc.edu/iiif/lcdl118967JPEG1jpg/canvas/0",
              "height": 2000,
              "width": 1516
            }
          ],
          "otherContent": [
            {
              "@context": "//iiif.io/api/presentation/2/context.json",
              "@id": "https://beta.lcdl.library.cofc.edu/lcdl/collections/annotation?iiif_identifier=lcdl118967JPEG1jpg",
              "@type": "sc:AnnotationList"
            }
          ]
        },
        {
          "@id": "https://rspace.library.cofc.edu/iiif/lcdl118968JPEG1jpg/canvas/0",
          "@type": "sc:Canvas",
          "label": "0",
          "height": 2000,
          "width": 1516,
          "thumbnail": {
            "@id": "https://iiif.library.cofc.edu/iiif/2/160882/full/thm/0/default.jpg",
            "@type": "dctypes:Image",
            "height": 150,
            "width": 114,
            "format": "image/jpeg",
            "service": {
              "@context": "http://iiif.io/api/image/2/context.json",
              "@id": "https://iiif.library.cofc.edu/iiif/2/160882",
              "profile": "http://iiif.io/api/image/2/level1.json"
            }
          },
          "images": [
            {
              "@context": "http://iiif.io/api/presentation/2/context.json",
              "@id": "https://rspace.library.cofc.edu/iiif/lcdl118968JPEG1jpg/annotation/0",
              "@type": "oa:Annotation",
              "motivation": "sc:painting",
              "resource": {
                "@id": "https://iiif.library.cofc.edu/iiif/2/160882/full/full/0/default.jpg",
                "@type": "dctypes:Image",
                "format": "image/jpeg",
                "service": {
                  "@context": "http://iiif.io/api/image/2/context.json",
                  "@id": "https://iiif.library.cofc.edu/iiif/2/160882",
                  "profile": "http://iiif.io/api/image/2/level1.json"
                }
              },
              "on": "https://rspace.library.cofc.edu/iiif/lcdl118968JPEG1jpg/canvas/0",
              "height": 2000,
              "width": 1516
            }
          ],
          "otherContent": [
            {
              "@context": "//iiif.io/api/presentation/2/context.json",
              "@id": "https://beta.lcdl.library.cofc.edu/lcdl/collections/annotation?iiif_identifier=lcdl118968JPEG1jpg",
              "@type": "sc:AnnotationList"
            }
          ]
        },
        {
          "@id": "https://rspace.library.cofc.edu/iiif/lcdl118969JPEG1jpg/canvas/0",
          "@type": "sc:Canvas",
          "label": "0",
          "height": 2000,
          "width": 1516,
          "thumbnail": {
            "@id": "https://iiif.library.cofc.edu/iiif/2/160883/full/thm/0/default.jpg",
            "@type": "dctypes:Image",
            "height": 150,
            "width": 114,
            "format": "image/jpeg",
            "service": {
              "@context": "http://iiif.io/api/image/2/context.json",
              "@id": "https://iiif.library.cofc.edu/iiif/2/160883",
              "profile": "http://iiif.io/api/image/2/level1.json"
            }
          },
          "images": [
            {
              "@context": "http://iiif.io/api/presentation/2/context.json",
              "@id": "https://rspace.library.cofc.edu/iiif/lcdl118969JPEG1jpg/annotation/0",
              "@type": "oa:Annotation",
              "motivation": "sc:painting",
              "resource": {
                "@id": "https://iiif.library.cofc.edu/iiif/2/160883/full/full/0/default.jpg",
                "@type": "dctypes:Image",
                "format": "image/jpeg",
                "service": {
                  "@context": "http://iiif.io/api/image/2/context.json",
                  "@id": "https://iiif.library.cofc.edu/iiif/2/160883",
                  "profile": "http://iiif.io/api/image/2/level1.json"
                }
              },
              "on": "https://rspace.library.cofc.edu/iiif/lcdl118969JPEG1jpg/canvas/0",
              "height": 2000,
              "width": 1516
            }
          ],
          "otherContent": [
            {
              "@context": "//iiif.io/api/presentation/2/context.json",
              "@id": "https://beta.lcdl.library.cofc.edu/lcdl/collections/annotation?iiif_identifier=lcdl118969JPEG1jpg",
              "@type": "sc:AnnotationList"
            }
          ]
        },
        {
          "@id": "https://rspace.library.cofc.edu/iiif/lcdl118970JPEG1jpg/canvas/0",
          "@type": "sc:Canvas",
          "label": "0",
          "height": 2000,
          "width": 1516,
          "thumbnail": {
            "@id": "https://iiif.library.cofc.edu/iiif/2/160884/full/thm/0/default.jpg",
            "@type": "dctypes:Image",
            "height": 150,
            "width": 114,
            "format": "image/jpeg",
            "service": {
              "@context": "http://iiif.io/api/image/2/context.json",
              "@id": "https://iiif.library.cofc.edu/iiif/2/160884",
              "profile": "http://iiif.io/api/image/2/level1.json"
            }
          },
          "images": [
            {
              "@context": "http://iiif.io/api/presentation/2/context.json",
              "@id": "https://rspace.library.cofc.edu/iiif/lcdl118970JPEG1jpg/annotation/0",
              "@type": "oa:Annotation",
              "motivation": "sc:painting",
              "resource": {
                "@id": "https://iiif.library.cofc.edu/iiif/2/160884/full/full/0/default.jpg",
                "@type": "dctypes:Image",
                "format": "image/jpeg",
                "service": {
                  "@context": "http://iiif.io/api/image/2/context.json",
                  "@id": "https://iiif.library.cofc.edu/iiif/2/160884",
                  "profile": "http://iiif.io/api/image/2/level1.json"
                }
              },
              "on": "https://rspace.library.cofc.edu/iiif/lcdl118970JPEG1jpg/canvas/0",
              "height": 2000,
              "width": 1516
            }
          ],
          "otherContent": [
            {
              "@context": "//iiif.io/api/presentation/2/context.json",
              "@id": "https://beta.lcdl.library.cofc.edu/lcdl/collections/annotation?iiif_identifier=lcdl118970JPEG1jpg",
              "@type": "sc:AnnotationList"
            }
          ]
        },
        {
          "@id": "https://rspace.library.cofc.edu/iiif/lcdl118971JPEG1jpg/canvas/0",
          "@type": "sc:Canvas",
          "label": "0",
          "height": 2000,
          "width": 1516,
          "thumbnail": {
            "@id": "https://iiif.library.cofc.edu/iiif/2/160885/full/thm/0/default.jpg",
            "@type": "dctypes:Image",
            "height": 150,
            "width": 114,
            "format": "image/jpeg",
            "service": {
              "@context": "http://iiif.io/api/image/2/context.json",
              "@id": "https://iiif.library.cofc.edu/iiif/2/160885",
              "profile": "http://iiif.io/api/image/2/level1.json"
            }
          },
          "images": [
            {
              "@context": "http://iiif.io/api/presentation/2/context.json",
              "@id": "https://rspace.library.cofc.edu/iiif/lcdl118971JPEG1jpg/annotation/0",
              "@type": "oa:Annotation",
              "motivation": "sc:painting",
              "resource": {
                "@id": "https://iiif.library.cofc.edu/iiif/2/160885/full/full/0/default.jpg",
                "@type": "dctypes:Image",
                "format": "image/jpeg",
                "service": {
                  "@context": "http://iiif.io/api/image/2/context.json",
                  "@id": "https://iiif.library.cofc.edu/iiif/2/160885",
                  "profile": "http://iiif.io/api/image/2/level1.json"
                }
              },
              "on": "https://rspace.library.cofc.edu/iiif/lcdl118971JPEG1jpg/canvas/0",
              "height": 2000,
              "width": 1516
            }
          ],
          "otherContent": [
            {
              "@context": "//iiif.io/api/presentation/2/context.json",
              "@id": "https://beta.lcdl.library.cofc.edu/lcdl/collections/annotation?iiif_identifier=lcdl118971JPEG1jpg",
              "@type": "sc:AnnotationList"
            }
          ]
        },
        {
          "@id": "https://rspace.library.cofc.edu/iiif/lcdl118972JPEG1jpg/canvas/0",
          "@type": "sc:Canvas",
          "label": "0",
          "height": 1516,
          "width": 2000,
          "thumbnail": {
            "@id": "https://iiif.library.cofc.edu/iiif/2/160886/full/thm/0/default.jpg",
            "@type": "dctypes:Image",
            "height": 114,
            "width": 150,
            "format": "image/jpeg",
            "service": {
              "@context": "http://iiif.io/api/image/2/context.json",
              "@id": "https://iiif.library.cofc.edu/iiif/2/160886",
              "profile": "http://iiif.io/api/image/2/level1.json"
            }
          },
          "images": [
            {
              "@context": "http://iiif.io/api/presentation/2/context.json",
              "@id": "https://rspace.library.cofc.edu/iiif/lcdl118972JPEG1jpg/annotation/0",
              "@type": "oa:Annotation",
              "motivation": "sc:painting",
              "resource": {
                "@id": "https://iiif.library.cofc.edu/iiif/2/160886/full/full/0/default.jpg",
                "@type": "dctypes:Image",
                "format": "image/jpeg",
                "service": {
                  "@context": "http://iiif.io/api/image/2/context.json",
                  "@id": "https://iiif.library.cofc.edu/iiif/2/160886",
                  "profile": "http://iiif.io/api/image/2/level1.json"
                }
              },
              "on": "https://rspace.library.cofc.edu/iiif/lcdl118972JPEG1jpg/canvas/0",
              "height": 1516,
              "width": 2000
            }
          ],
          "otherContent": [
            {
              "@context": "//iiif.io/api/presentation/2/context.json",
              "@id": "https://beta.lcdl.library.cofc.edu/lcdl/collections/annotation?iiif_identifier=lcdl118972JPEG1jpg",
              "@type": "sc:AnnotationList"
            }
          ]
        },
        {
          "@id": "https://rspace.library.cofc.edu/iiif/lcdl118973JPEG1jpg/canvas/0",
          "@type": "sc:Canvas",
          "label": "0",
          "height": 1516,
          "width": 2000,
          "thumbnail": {
            "@id": "https://iiif.library.cofc.edu/iiif/2/160887/full/thm/0/default.jpg",
            "@type": "dctypes:Image",
            "height": 114,
            "width": 150,
            "format": "image/jpeg",
            "service": {
              "@context": "http://iiif.io/api/image/2/context.json",
              "@id": "https://iiif.library.cofc.edu/iiif/2/160887",
              "profile": "http://iiif.io/api/image/2/level1.json"
            }
          },
          "images": [
            {
              "@context": "http://iiif.io/api/presentation/2/context.json",
              "@id": "https://rspace.library.cofc.edu/iiif/lcdl118973JPEG1jpg/annotation/0",
              "@type": "oa:Annotation",
              "motivation": "sc:painting",
              "resource": {
                "@id": "https://iiif.library.cofc.edu/iiif/2/160887/full/full/0/default.jpg",
                "@type": "dctypes:Image",
                "format": "image/jpeg",
                "service": {
                  "@context": "http://iiif.io/api/image/2/context.json",
                  "@id": "https://iiif.library.cofc.edu/iiif/2/160887",
                  "profile": "http://iiif.io/api/image/2/level1.json"
                }
              },
              "on": "https://rspace.library.cofc.edu/iiif/lcdl118973JPEG1jpg/canvas/0",
              "height": 1516,
              "width": 2000
            }
          ],
          "otherContent": [
            {
              "@context": "//iiif.io/api/presentation/2/context.json",
              "@id": "https://beta.lcdl.library.cofc.edu/lcdl/collections/annotation?iiif_identifier=lcdl118973JPEG1jpg",
              "@type": "sc:AnnotationList"
            }
          ]
        },
        {
          "@id": "https://rspace.library.cofc.edu/iiif/lcdl118974JPEG1jpg/canvas/0",
          "@type": "sc:Canvas",
          "label": "0",
          "height": 1516,
          "width": 2000,
          "thumbnail": {
            "@id": "https://iiif.library.cofc.edu/iiif/2/160888/full/thm/0/default.jpg",
            "@type": "dctypes:Image",
            "height": 114,
            "width": 150,
            "format": "image/jpeg",
            "service": {
              "@context": "http://iiif.io/api/image/2/context.json",
              "@id": "https://iiif.library.cofc.edu/iiif/2/160888",
              "profile": "http://iiif.io/api/image/2/level1.json"
            }
          },
          "images": [
            {
              "@context": "http://iiif.io/api/presentation/2/context.json",
              "@id": "https://rspace.library.cofc.edu/iiif/lcdl118974JPEG1jpg/annotation/0",
              "@type": "oa:Annotation",
              "motivation": "sc:painting",
              "resource": {
                "@id": "https://iiif.library.cofc.edu/iiif/2/160888/full/full/0/default.jpg",
                "@type": "dctypes:Image",
                "format": "image/jpeg",
                "service": {
                  "@context": "http://iiif.io/api/image/2/context.json",
                  "@id": "https://iiif.library.cofc.edu/iiif/2/160888",
                  "profile": "http://iiif.io/api/image/2/level1.json"
                }
              },
              "on": "https://rspace.library.cofc.edu/iiif/lcdl118974JPEG1jpg/canvas/0",
              "height": 1516,
              "width": 2000
            }
          ],
          "otherContent": [
            {
              "@context": "//iiif.io/api/presentation/2/context.json",
              "@id": "https://beta.lcdl.library.cofc.edu/lcdl/collections/annotation?iiif_identifier=lcdl118974JPEG1jpg",
              "@type": "sc:AnnotationList"
            }
          ]
        },
        {
          "@id": "https://rspace.library.cofc.edu/iiif/lcdl118975JPEG1jpg/canvas/0",
          "@type": "sc:Canvas",
          "label": "0",
          "height": 1516,
          "width": 2000,
          "thumbnail": {
            "@id": "https://iiif.library.cofc.edu/iiif/2/160889/full/thm/0/default.jpg",
            "@type": "dctypes:Image",
            "height": 114,
            "width": 150,
            "format": "image/jpeg",
            "service": {
              "@context": "http://iiif.io/api/image/2/context.json",
              "@id": "https://iiif.library.cofc.edu/iiif/2/160889",
              "profile": "http://iiif.io/api/image/2/level1.json"
            }
          },
          "images": [
            {
              "@context": "http://iiif.io/api/presentation/2/context.json",
              "@id": "https://rspace.library.cofc.edu/iiif/lcdl118975JPEG1jpg/annotation/0",
              "@type": "oa:Annotation",
              "motivation": "sc:painting",
              "resource": {
                "@id": "https://iiif.library.cofc.edu/iiif/2/160889/full/full/0/default.jpg",
                "@type": "dctypes:Image",
                "format": "image/jpeg",
                "service": {
                  "@context": "http://iiif.io/api/image/2/context.json",
                  "@id": "https://iiif.library.cofc.edu/iiif/2/160889",
                  "profile": "http://iiif.io/api/image/2/level1.json"
                }
              },
              "on": "https://rspace.library.cofc.edu/iiif/lcdl118975JPEG1jpg/canvas/0",
              "height": 1516,
              "width": 2000
            }
          ],
          "otherContent": [
            {
              "@context": "//iiif.io/api/presentation/2/context.json",
              "@id": "https://beta.lcdl.library.cofc.edu/lcdl/collections/annotation?iiif_identifier=lcdl118975JPEG1jpg",
              "@type": "sc:AnnotationList"
            }
          ]
        },
        {
          "@id": "https://rspace.library.cofc.edu/iiif/lcdl118976JPEG1jpg/canvas/0",
          "@type": "sc:Canvas",
          "label": "0",
          "height": 1516,
          "width": 2000,
          "thumbnail": {
            "@id": "https://iiif.library.cofc.edu/iiif/2/160890/full/thm/0/default.jpg",
            "@type": "dctypes:Image",
            "height": 114,
            "width": 150,
            "format": "image/jpeg",
            "service": {
              "@context": "http://iiif.io/api/image/2/context.json",
              "@id": "https://iiif.library.cofc.edu/iiif/2/160890",
              "profile": "http://iiif.io/api/image/2/level1.json"
            }
          },
          "images": [
            {
              "@context": "http://iiif.io/api/presentation/2/context.json",
              "@id": "https://rspace.library.cofc.edu/iiif/lcdl118976JPEG1jpg/annotation/0",
              "@type": "oa:Annotation",
              "motivation": "sc:painting",
              "resource": {
                "@id": "https://iiif.library.cofc.edu/iiif/2/160890/full/full/0/default.jpg",
                "@type": "dctypes:Image",
                "format": "image/jpeg",
                "service": {
                  "@context": "http://iiif.io/api/image/2/context.json",
                  "@id": "https://iiif.library.cofc.edu/iiif/2/160890",
                  "profile": "http://iiif.io/api/image/2/level1.json"
                }
              },
              "on": "https://rspace.library.cofc.edu/iiif/lcdl118976JPEG1jpg/canvas/0",
              "height": 1516,
              "width": 2000
            }
          ],
          "otherContent": [
            {
              "@context": "//iiif.io/api/presentation/2/context.json",
              "@id": "https://beta.lcdl.library.cofc.edu/lcdl/collections/annotation?iiif_identifier=lcdl118976JPEG1jpg",
              "@type": "sc:AnnotationList"
            }
          ]
        },
        {
          "@id": "https://rspace.library.cofc.edu/iiif/lcdl118977JPEG1jpg/canvas/0",
          "@type": "sc:Canvas",
          "label": "0",
          "height": 2000,
          "width": 1516,
          "thumbnail": {
            "@id": "https://iiif.library.cofc.edu/iiif/2/160891/full/thm/0/default.jpg",
            "@type": "dctypes:Image",
            "height": 150,
            "width": 114,
            "format": "image/jpeg",
            "service": {
              "@context": "http://iiif.io/api/image/2/context.json",
              "@id": "https://iiif.library.cofc.edu/iiif/2/160891",
              "profile": "http://iiif.io/api/image/2/level1.json"
            }
          },
          "images": [
            {
              "@context": "http://iiif.io/api/presentation/2/context.json",
              "@id": "https://rspace.library.cofc.edu/iiif/lcdl118977JPEG1jpg/annotation/0",
              "@type": "oa:Annotation",
              "motivation": "sc:painting",
              "resource": {
                "@id": "https://iiif.library.cofc.edu/iiif/2/160891/full/full/0/default.jpg",
                "@type": "dctypes:Image",
                "format": "image/jpeg",
                "service": {
                  "@context": "http://iiif.io/api/image/2/context.json",
                  "@id": "https://iiif.library.cofc.edu/iiif/2/160891",
                  "profile": "http://iiif.io/api/image/2/level1.json"
                }
              },
              "on": "https://rspace.library.cofc.edu/iiif/lcdl118977JPEG1jpg/canvas/0",
              "height": 2000,
              "width": 1516
            }
          ],
          "otherContent": [
            {
              "@context": "//iiif.io/api/presentation/2/context.json",
              "@id": "https://beta.lcdl.library.cofc.edu/lcdl/collections/annotation?iiif_identifier=lcdl118977JPEG1jpg",
              "@type": "sc:AnnotationList"
            }
          ]
        }
      ]
    }
  ]
}